ransack/__init__.py
ransack/exceptions.py
ransack/function.py
ransack/operator.py
ransack/parser.py
ransack/py.typed
ransack/transformer.py
ransacklib-1.0.0.dist-info/licenses/LICENSE
ransacklib-1.0.0.dist-info/METADATA
ransacklib-1.0.0.dist-info/WHEEL
ransacklib-1.0.0.dist-info/top_level.txt
ransacklib-1.0.0.dist-info/RECORD
