Metadata-Version: 2.4
Name: ransacklib
Version: 1.0.0
Summary: A modern, extensible language for manipulation with structured data
Author-email: "Rajmund H. Hruška" <rajmund.hruska@cesnet.cz>
License-Expression: MIT
Project-URL: Repository, https://gitlab.cesnet.cz/713/mentat/ransack
Project-URL: Documentation, https://ransack-125e0a.gitlab-pages.cesnet.cz/index.html
Project-URL: Issues, https://gitlab.cesnet.cz/713/mentat/ransack/-/issues
Classifier: Programming Language :: Python :: 3
Classifier: Topic :: Software Development :: Libraries :: Python Modules
Classifier: Intended Audience :: Developers
Classifier: Operating System :: OS Independent
Requires-Python: >=3.10
License-File: LICENSE
Requires-Dist: lark<1.3.0,>=1.2.2
Requires-Dist: ipranges<0.2,>=0.1.12
Provides-Extra: dev
Requires-Dist: pytest; extra == "dev"
Requires-Dist: pytest-cov; extra == "dev"
Requires-Dist: sphinx; extra == "dev"
Requires-Dist: sphinx_rtd_theme; extra == "dev"
Requires-Dist: mypy; extra == "dev"
Requires-Dist: ruff; extra == "dev"
Requires-Dist: build; extra == "dev"
Requires-Dist: twine; extra == "dev"
Dynamic: license-file
